{
  "db_name": "PostgreSQL",
  "query": "\n        SELECT id, mode as \"mode: GameMode\", status as \"status: GameStatus\",\n               join_code, created_by, created_at, started_at, ended_at, settings, total_score\n        FROM games WHERE join_code = $1\n        ",
  "describe": {
    "columns": [
      {
        "ordinal": 0,
        "name": "id",
        "type_info": "Varchar"
      },
      {
        "ordinal": 1,
        "name": "mode: GameMode",
        "type_info": {
          "Custom": {
            "name": "game_mode",
            "kind": {
              "Enum": [
                "solo",
                "multiplayer",
                "challenge"
              ]
            }
          }
        }
      },
      {
        "ordinal": 2,
        "name": "status: GameStatus",
        "type_info": {
          "Custom": {
            "name": "game_status",
            "kind": {
              "Enum": [
                "lobby",
                "active",
                "finished",
                "abandoned"
              ]
            }
          }
        }
      },
      {
        "ordinal": 3,
        "name": "join_code",
        "type_info": "Varchar"
      },
      {
        "ordinal": 4,
        "name": "created_by",
        "type_info": "Varchar"
      },
      {
        "ordinal": 5,
        "name": "created_at",
        "type_info": "Timestamptz"
      },
      {
        "ordinal": 6,
        "name": "started_at",
        "type_info": "Timestamptz"
      },
      {
        "ordinal": 7,
        "name": "ended_at",
        "type_info": "Timestamptz"
      },
      {
        "ordinal": 8,
        "name": "settings",
        "type_info": "Jsonb"
      },
      {
        "ordinal": 9,
        "name": "total_score",
        "type_info": "Int4"
      }
    ],
    "parameters": {
      "Left": [
        "Text"
      ]
    },
    "nullable": [
      false,
      false,
      false,
      true,
      false,
      false,
      true,
      true,
      false,
      true
    ]
  },
  "hash": "cadee0dd048a41bb5bc720225f57ae65e7706e56883185c45ac5c5477c4abf0d"
}
